pindo_cli/__init__.py
pindo_cli/cli.py
pindo_cli/http.py
pindo_cli-0.2.0.dist-info/entry_points.txt
pindo_cli-0.2.0.dist-info/LICENSE
pindo_cli-0.2.0.dist-info/WHEEL
pindo_cli-0.2.0.dist-info/METADATA
pindo_cli-0.2.0.dist-info/RECORD
