Metadata-Version: 2.1
Name: pindo-cli
Version: 0.2.0
Summary: A simple Command Line Interface that allows you to authenticate with the Pindo API.
Home-page: https://github.com/pindoio/pindo-cli
License: MIT
Keywords: agile,standup
Author: Team Pindo
Author-email: team@pindo.io
Requires-Python: >=3.7,<4.0
Classifier: Environment :: Console
Classifier: Intended Audience :: Developers
Classifier: License :: OSI Approved :: MIT License
Classifier: Operating System :: MacOS
Classifier: Operating System :: Microsoft :: Windows
Classifier: Operating System :: POSIX :: Linux
Classifier: Programming Language :: Python :: 3
Classifier: Programming Language :: Python :: 3.7
Classifier: Programming Language :: Python :: 3.8
Classifier: Programming Language :: Python :: 3.9
Requires-Dist: click-spinner (>=0.1.10,<0.2.0)
Requires-Dist: click8 (>=8.0.1,<9.0.0)
Requires-Dist: requests (>=2.25.1,<3.0.0)
Requires-Dist: rich (>=10.6.0,<11.0.0)
Requires-Dist: tomlkit (>=0.7.0,<0.8.0)
Project-URL: Documentation, https://github.com/pindoio/pindo-cli
Project-URL: Repository, https://github.com/pindoio/pindo-cli
